fastDjango/__init__.py
fastDjango/main.py
fastDjango-0.0.1.dist-info/LICENSE
fastDjango-0.0.1.dist-info/METADATA
fastDjango-0.0.1.dist-info/WHEEL
fastDjango-0.0.1.dist-info/top_level.txt
fastDjango-0.0.1.dist-info/RECORD
