Metadata-Version: 2.1
Name: fastDjango
Version: 0.0.1
Summary: Fast Django Package, Alpha.
Author: DukeDonut
Classifier: Programming Language :: Python :: 3
Classifier: License :: OSI Approved :: MIT License
Classifier: Operating System :: OS Independent
Requires-Python: >=3.5
License-File: LICENSE
